AUTHORS.rst
LICENSE.txt
MANIFEST.in
README.rst
pyproject.toml
setup.cfg
setup.py
.github/workflows/main.yml
megara_tools.egg-info/PKG-INFO
megara_tools.egg-info/SOURCES.txt
megara_tools.egg-info/dependency_links.txt
megara_tools.egg-info/entry_points.txt
megara_tools.egg-info/requires.txt
megara_tools.egg-info/top_level.txt
megaratools/__init__.py
megaratools/analyze.py
megaratools/analyze_rss.py
megaratools/analyze_spectrum.py
megaratools/diffuse_light.py
megaratools/extract_elliptical_rings_spectrum.py
megaratools/extract_spectrum.py
megaratools/hypercube.py
megaratools/plot_spectrum.py
megaratools/rss_arith.py