Metadata-Version: 2.1
Name: megara-tools
Version: 0.1.1
Summary: Analysis and visualization of data from MEGARA instrument
Home-page: https://github.com/guaix-ucm/megara-tools
Author: Armando Gil de Paz
Author-email: agil@fis.ucm.es
Maintainer: Sergio Pascual
Maintainer-email: sergiopr@fis.ucm.es
License: GPLv3
Platform: UNKNOWN
Classifier: Programming Language :: Python :: 3.5
Classifier: Programming Language :: Python :: 3.6
Classifier: Programming Language :: Python :: 3.7
Classifier: Programming Language :: Python :: 3.8
Classifier: Development Status :: 3 - Alpha
Classifier: Environment :: Console
Classifier: Intended Audience :: Science/Research
Classifier: License :: OSI Approved :: GNU General Public License (GPL)
Classifier: Operating System :: OS Independent
Classifier: Topic :: Scientific/Engineering :: Astronomy
Provides-Extra: hypercube
